ezbolt/__init__.py
ezbolt/bolt.py
ezbolt/boltgroup.py
ezbolt/plotter.py
ezbolt-0.3.0.dist-info/METADATA
ezbolt-0.3.0.dist-info/WHEEL
ezbolt-0.3.0.dist-info/licenses/LICENSE
ezbolt-0.3.0.dist-info/RECORD
