Metadata-Version: 2.4
Name: ezbolt
Version: 0.3.0
Summary: ezbolt - bolt force calculations in python
Project-URL: Homepage, https://github.com/wcfrobert/ezbolt
Project-URL: Bug Tracker, https://github.com/wcfrobert/ezbolt/issues
Author-email: wcfrobert <temprobertdev@gmail.com>
License-File: LICENSE
Keywords: bolt force,elastic method,instant center of rotation,steel connection,structural engineering
Classifier: License :: OSI Approved :: MIT License
Classifier: Operating System :: OS Independent
Classifier: Programming Language :: Python :: 3
Requires-Python: >=3.7
Requires-Dist: matplotlib>=3.0
Requires-Dist: numpy>=1.0
Requires-Dist: pandas>=2.0
